[
  {
    "id": 599657419,
    "frameworks": ["React", "Styled-Componets", "Firebase"],
    "filosophy": {
      "phrase": "Geometry allows us to explore and comprehend the fundamental properties of space, revealing the underlying beauty and order in our universe.. ",
      "author": "Henri Poincaré"
    },
    "gallery": [
      {
        "title": "Mobile",
        "isMP4": false,
        "size": 1
      },
      {
        "title": "Desktop",
        "isMP4": false,
        "size": 2
      },
      {
        "title": "Loading",
        "isMP4": true,
        "size": 3
      }
    ]
  },
  {
    "id": 617670848,
    "frameworks": ["React", "Firebase"],
    "filosophy": {
      "phrase": "some phrase",
      "author": "René Descartes"
    },
    "gallery": [
      {
        "title": "Desktop",
        "isMP4": false,
        "size": 3
      },
      {
        "title": "Desktop",
        "isMP4": false,
        "size": 3
      },
      {
        "title": "Desktop",
        "isMP4": false,
        "size": 3
      }
    ]
  },
  {
    "id": 624459441,
    "frameworks": ["Next.js", "Tailwind", "MongoDb", "Node"],
    "filosophy": {
      "phrase": "Eureka!",
      "author": "Archimedes of Syracuse"
    },
    "gallery": [
      {
        "title": "Intro",
        "isMP4": true,
        "size": 3
      },
      {
        "title": "Overview",
        "isMP4": true,
        "size": 3
      },
      {
        "title": "Plant Route",
        "isMP4": false,
        "size": 2
      }
    ]
  },
  {
    "id": 617668310,
    "frameworks": ["Next.js"],
    "filosophy": {
      "phrase": "I can calculate the motion of heavenly bodies, but not the madness of people.",
      "author": "Isaac Newton"
    },
    "gallery": [
      {
        "title": "Desktop",
        "isMP4": false,
        "size": 3
      },
      {
        "title": "Desktop",
        "isMP4": false,
        "size": 3
      },
      {
        "title": "Desktop",
        "isMP4": false,
        "size": 3
      }
    ]
  },
  {
    "id": 12998282,
    "frameworks": ["Next.js", "MongoDb", "Tailwind"],
    "filosophy": {
      "phrase": "Imagination is more important than knowledge. For knowledge is limited, whereas imagination embraces the entire world.",
      "author": "Henri Poincaré"
    },
    "gallery": [
      {
        "title": "Desktop",
        "isMP4": false,
        "size": 3
      },
      {
        "title": "Desktop",
        "isMP4": false,
        "size": 3
      },
      {
        "title": "Desktop",
        "isMP4": false,
        "size": 3
      }
    ]
  },
  {
    "id": 1,
    "frameworks": ["React", ""],
    "filosophy": {
      "phrase": "some phrase",
      "author": "Rene Descartes"
    },
    "gallery": [
      {
        "title": "Desktop",
        "isMP4": false,
        "size": 3
      },
      {
        "title": "Desktop",
        "isMP4": false,
        "size": 3
      },
      {
        "title": "Desktop",
        "isMP4": false,
        "size": 3
      }
    ]
  }
]
